{"status": "ok", "totalResults": 3, "articles": [{"source": {"id": null, "name": "[Removed]"}, "author": null, "title": "[Removed]", "description": "[Removed]", "url": "https://removed.com", "urlToImage": null, "publishedAt": "1970-01-01T00:00:00Z", "content": "[Removed]"}, {"source": {"id": null, "name": "[Removed]"}, "author": null, "title": "[Removed]", "description": "[Removed]", "url": "https://removed.com", "urlToImage": null, "publishedAt": "1970-01-01T00:00:00Z", "content": "[Removed]"}, {"source": {"id": null, "name": "BBC News"}, "author": null, "title": "Kevin Hart's Northern Ireland based movie released on Netflix - BBC.com", "description": "Ulster University, Titanic Hotel and the Crown bar in Belfast are among the movie's locations.", "url": "https://www.bbc.com/news/uk-northern-ireland-67950087", "urlToImage": "https://ichef.bbci.co.uk/news/1024/branded_news/A386/production/_116926814_gettyimages-1193044293.jpg", "publishedAt": "2024-01-12T09:31:00Z", "content": "Kevin Hart is one of the most successful comedy actors in Hollywood\r\nThe new Kevin Hart movie Lift, filmed largely in Northern Ireland, has been released on Netflix.\r\nThe US comedian spent a few mont\u2026 [+3170 chars]"}]}