{"status": "ok", "totalResults": 2, "articles": [{"source": {"id": "independent", "name": "Independent"}, "author": "Nicole Vassell", "title": "Sam Levinson's self-hyped The Idol opens to dismal Rotten Tomatoes score - The Independent", "description": "\u2018Euphoria\u2019 creator has already dubbed new series \u2018the show of the summer\u2019", "url": "https://www.independent.co.uk/arts-entertainment/tv/news/the-idol-rotten-tomatoes-score-reviews-b2344544.html", "urlToImage": "https://static.independent.co.uk/2023/05/09/09/newFile.jpg?quality=75&width=1200&auto=webp", "publishedAt": "2023-05-24T03:29:22Z", "content": "Sign up to our free IndyArts newsletter for all the latest entertainment news and reviews\r\nSign up to our free IndyArts newsletter\r\nThe Idol has been greeted with a less-than-desirable response after\u2026 [+1952 chars]"}, {"source": {"id": null, "name": "YouTube"}, "author": null, "title": "Prince Harry & Meghan Markle's Rep RESPONDS To 'Abhorrent' Claims That Car Chase Was PR Stunt - ET Canada", "description": "Nearly one week after Prince Harry and Meghan Markle\u2019s \u201cnear catastrophic\u201d car chase in New York City, Gayle King defends the royal couple amid people trying...", "url": "https://www.youtube.com/watch?v=F23rPDJFEWM", "urlToImage": "https://i.ytimg.com/vi/F23rPDJFEWM/hqdefault.jpg", "publishedAt": "2023-05-23T17:58:51Z", "content": null}]}