{"status": "ok", "totalResults": 3, "articles": [{"source": {"id": null, "name": "[Removed]"}, "author": null, "title": "[Removed]", "description": "[Removed]", "url": "https://removed.com", "urlToImage": null, "publishedAt": "1970-01-01T00:00:00", "content": "[Removed]"}, {"source": {"id": null, "name": "digitalspy.com"}, "author": "George Lewis", "title": "Emma Stone had no hesitation over new movie's sex scenes - Digital Spy", "description": "\"We had to be confident Emma had no shame about her body.\"", "url": "https://www.digitalspy.com/movies/a44981543/emma-stone-poor-things-sex-scenes/", "urlToImage": "https://hips.hearstapps.com/hmg-prod/images/poor-things-emma-stone-645ceddd5b51b.jpg?crop=0.875xw:0.354xh;0.0977xw,0.469xh&resize=1200:*", "publishedAt": "2023-09-02T21:46:28Z", "content": "Poor Thingsdirector Yorgos Lanthimos has revealed that star Emma Stone didn't hesitate when filming the sex scenes in the new movie.\r\nThe pair have reunited following their 2018 collaboration on The \u2026 [+2630 chars]"}, {"source": {"id": null, "name": "[Removed]"}, "author": null, "title": "[Removed]", "description": "[Removed]", "url": "https://removed.com", "urlToImage": null, "publishedAt": "1970-01-01T00:00:00", "content": "[Removed]"}]}