{"status": "ok", "totalResults": 5, "articles": [{"source": {"id": null, "name": "[Removed]"}, "author": null, "title": "[Removed]", "description": "[Removed]", "url": "https://removed.com", "urlToImage": null, "publishedAt": "1970-01-01T00:00:00Z", "content": "[Removed]"}, {"source": {"id": null, "name": "[Removed]"}, "author": null, "title": "[Removed]", "description": "[Removed]", "url": "https://removed.com", "urlToImage": null, "publishedAt": "1970-01-01T00:00:00Z", "content": "[Removed]"}, {"source": {"id": null, "name": "YouTube"}, "author": null, "title": "CM Punk and Cody Rhodes are set for face-to-face on Raw: WWE Now, Jan. 22, 2024 - WWE", "description": "WWE Now previews meeting between CM Punk and Cody Rhodes, Seth \u201cFreakin\u201d Rollins\u2019 address to the WWE Universe, a showdown between Drew McIntyre and Damian Pr...", "url": "https://www.youtube.com/watch?v=XQfqCYa-T_8", "urlToImage": "https://i.ytimg.com/vi/XQfqCYa-T_8/maxresdefault.jpg", "publishedAt": "2024-01-22T22:13:27Z", "content": null}, {"source": {"id": null, "name": "[Removed]"}, "author": null, "title": "[Removed]", "description": "[Removed]", "url": "https://removed.com", "urlToImage": null, "publishedAt": "1970-01-01T00:00:00Z", "content": "[Removed]"}, {"source": {"id": "mashable", "name": "Mashable"}, "author": "Mashable Team", "title": "Wordle today: Here's the answer and hints for January 22 - Mashable", "description": "Here are some tips and tricks to help you find the answer to \"Wordle\" #947.", "url": "https://mashable.com/article/wordle-today-answer-january-22-2024", "urlToImage": "https://helios-i.mashable.com/imagery/articles/02tryZ9IYY5rSPSrutsnobw/hero-image.fill.size_1200x675.v1705791177.jpg", "publishedAt": "2024-01-22T02:08:35Z", "content": null}]}