{"status": "ok", "totalResults": 4, "articles": [{"source": {"id": null, "name": "[Removed]"}, "author": null, "title": "[Removed]", "description": "[Removed]", "url": "https://removed.com", "urlToImage": null, "publishedAt": "1970-01-01T00:00:00Z", "content": "[Removed]"}, {"source": {"id": null, "name": "Startefacts.com"}, "author": null, "title": "When Adaptations Go Wrong: 15 Book-to-Movie Flops - Startefacts", "description": "Looks like sometimes a book just does not translate to the big screen at all.", "url": "https://startefacts.com/news/when-adaptations-go-wrong-15-book-to-movie-flops_a117", "urlToImage": "https://startefacts.com/upload//upload/news/469745568468.jpg", "publishedAt": "2023-09-16T15:58:09Z", "content": "Looks like sometimes a book just does not translate to the big screen at all.\r\n1. \"The Host\" (2013)\r\nStephenie Meyer switched from vampires to aliens. Maybe she should've stuck with vampires. $63 mil\u2026 [+13356 chars]"}, {"source": {"id": null, "name": "[Removed]"}, "author": null, "title": "[Removed]", "description": "[Removed]", "url": "https://removed.com", "urlToImage": null, "publishedAt": "1970-01-01T00:00:00Z", "content": "[Removed]"}, {"source": {"id": null, "name": "[Removed]"}, "author": null, "title": "[Removed]", "description": "[Removed]", "url": "https://removed.com", "urlToImage": null, "publishedAt": "1970-01-01T00:00:00Z", "content": "[Removed]"}]}