{"status": "ok", "totalResults": 1, "articles": [{"source": {"id": null, "name": "YouTube"}, "author": null, "title": "One of The GREAT Test Innings | Ollie Pope on Sensational 196 & Hyderabad Win | India v England - England & Wales Cricket Board", "description": "Ollie Pope speaks to us after our victory in the first Test over India.Find out more at ecb.co.ukThis is the official channel of the ECB. Watch all the lates...", "url": "https://www.youtube.com/watch?v=ZLTzctisui8", "urlToImage": "https://i.ytimg.com/vi/ZLTzctisui8/maxresdefault.jpg", "publishedAt": "2024-01-29T10:31:58Z", "content": null}]}