{"status": "ok", "totalResults": 1, "articles": [{"source": {"id": null, "name": "ScienceAlert"}, "author": "Michelle Starr", "title": "Rare Sky Explosion Coming Soon: a Once-in-a-Lifetime Event Visible to The Naked Eye - ScienceAlert", "description": "Sometime in the next few months, a spectacle could light up the northern sky.", "url": "https://www.sciencealert.com/rare-sky-explosion-coming-soon-a-once-in-a-lifetime-event-visible-to-the-naked-eye", "urlToImage": "https://www.sciencealert.com/images/2024/06/classical-nova.jpg", "publishedAt": "2024-06-19T03:32:47Z", "content": "Sometime in the next few months, a spectacle could light up the northern sky.\r\nThere, in the Corona Borealis constellation, at a distance of more than 2,500 light-years, a star called T Coronae Borea\u2026 [+3870 chars]"}]}