{"status": "ok", "totalResults": 3, "articles": [{"source": {"id": null, "name": "[Removed]"}, "author": null, "title": "[Removed]", "description": "[Removed]", "url": "https://removed.com", "urlToImage": null, "publishedAt": "1970-01-01T00:00:00Z", "content": "[Removed]"}, {"source": {"id": null, "name": "[Removed]"}, "author": null, "title": "[Removed]", "description": "[Removed]", "url": "https://removed.com", "urlToImage": null, "publishedAt": "1970-01-01T00:00:00Z", "content": "[Removed]"}, {"source": {"id": null, "name": "SciTechDaily"}, "author": null, "title": "Astronomical Illusions: New Images Reveal What Neptune and Uranus Really Look Like - SciTechDaily", "description": "Recent research led by Professor Patrick Irwin shows that Neptune and Uranus are both a similar shade of greenish-blue, challenging previous perceptions of their colors. The study used modern telescopic data to correct historical color inaccuracies and explai\u2026", "url": "https://scitechdaily.com/astronomical-illusions-new-images-reveal-what-neptune-and-uranus-really-look-like/", "urlToImage": "https://scitechdaily.com/images/Neptune-and-Uranus-True-Colors.jpg", "publishedAt": "2024-01-07T09:42:41Z", "content": "A study reveals Neptune and Uranus are both greenish-blue, not the deep azure and pale cyan previously believed. Modern telescope data was used to correct these historical color misrepresentations. C\u2026 [+8848 chars]"}]}