{"status": "ok", "totalResults": 4, "articles": [{"source": {"id": null, "name": "[Removed]"}, "author": null, "title": "[Removed]", "description": "[Removed]", "url": "https://removed.com", "urlToImage": null, "publishedAt": "1970-01-01T00:00:00Z", "content": "[Removed]"}, {"source": {"id": null, "name": "YouTube"}, "author": null, "title": "Apple WWDC 2024 preview: All in on AI | Engadget Podcast - Engadget", "description": "We're gearing up to cover Apple's Worldwide Developers Conference (WWDC) next week! In this episode, Cherlynn and Devindra dive into everything they expect a...", "url": "https://www.youtube.com/watch?v=AogWbUmC4ww", "urlToImage": "https://i.ytimg.com/vi/AogWbUmC4ww/maxresdefault.jpg", "publishedAt": "2024-06-06T16:23:51Z", "content": null}, {"source": {"id": "ign", "name": "IGN"}, "author": "Wesley Yin-Poole", "title": "Helldivers 2 Reveals Jungle-Themed Premium Warbond, Viper Commandos \u2014 Here's What to Expect - IGN", "description": "Helldivers 2 has revealed the Viper Commandos Premium Warbond. Here's what to expect.", "url": "https://www.ign.com/articles/helldivers-2-reveals-jungle-themed-premium-warbond-viper-commandos-heres-what-to-expect", "urlToImage": "https://assets-prd.ignimgs.com/2024/06/06/hd-main-1717678230233.png?width=1280", "publishedAt": "2024-06-06T12:56:23Z", "content": "Helldivers 2 developer Arrowhead has revealed the games next Premium Warbond, dubbed Viper Commandos and due out June 13.\r\nIn a post on the PlayStation Blog, Katherine Baskin, social media and commun\u2026 [+4678 chars]"}, {"source": {"id": null, "name": "[Removed]"}, "author": null, "title": "[Removed]", "description": "[Removed]", "url": "https://removed.com", "urlToImage": null, "publishedAt": "1970-01-01T00:00:00Z", "content": "[Removed]"}]}