{"status": "ok", "totalResults": 1, "articles": [{"source": {"id": null, "name": "Cyclingnews.com"}, "author": "Jackie Tyson", "title": "'Incredible' push from ex-skiing teammate pivotal for Roglic's Giro d'Italia win - Cyclingnews", "description": "Slovenian gets surprise assist from countryman Mitja Me\u017enar, who says 'I reacted completely instinctively'", "url": "https://www.cyclingnews.com/news/incredible-push-from-ex-skiing-teammate-pivotal-for-roglics-giro-ditalia-win/", "urlToImage": "https://cdn.mos.cms.futurecdn.net/qLpotQMbkwcYX6mjxsh4tQ-1200-80.jpg", "publishedAt": "2023-05-29T15:32:45Z", "content": "Primo\u017e Rogli\u010d once again proved he can fly up, and down, mountains, whether it be on a bike or on skis. In this year\u2019s decisive individual time trial at the Giro d'Italia to the top of Monte Lussari,\u2026 [+3121 chars]"}]}