{"status": "ok", "totalResults": 2, "articles": [{"source": {"id": null, "name": "[Removed]"}, "author": null, "title": "[Removed]", "description": "[Removed]", "url": "https://removed.com", "urlToImage": null, "publishedAt": "1970-01-01T00:00:00Z", "content": "[Removed]"}, {"source": {"id": null, "name": "YouTube"}, "author": null, "title": "Buttler Ton In Thrilling Run Chase | 206 to Win | England v Australia 2018 - England & Wales Cricket Board", "description": "Watch mini highlights of the England batting chase from 2018 against Australia. Find out more at ecb.co.ukThis is the official channel of the ECB. Watch all ...", "url": "https://www.youtube.com/watch?v=jwLZIVL4fIY", "urlToImage": "https://i.ytimg.com/vi/jwLZIVL4fIY/maxresdefault.jpg", "publishedAt": "2023-11-03T06:00:17Z", "content": null}]}