{"status": "ok", "totalResults": 1, "articles": [{"source": {"id": null, "name": "Ageasbowl.com"}, "author": null, "title": "Match Preview: Warwickshire v Hampshire, Metro Bank One Day Cup Semi-Final - The Ageas Bowl", "description": "Match Preview: Warwickshire v Hampshire, Metro Bank One Day Cup Semi-Final", "url": "https://www.ageasbowl.com/cricket/news/match-preview-warwickshire-v-hampshire,-metro-bank-one-day-cup-semi-final/", "urlToImage": "https://ageasbowl.adidocdn.dev/2023/Cricket/News Preview (480x380)/Aug 23/HC 50OVER MatchdayGraphics SFWarwickshire(H) MatchPreview 480x380 v1 240823.jpg", "publishedAt": "2023-08-28T15:01:53Z", "content": "Warwickshire v HampshireMetro Bank One Day Cup Semi-FinalTuesday 29th August\u00a0(11am Start)Edgbaston\r\nHampshire travel to Edgbaston to take on Warwickshire for a place in the Metro Bank One Day Cup fin\u2026 [+2638 chars]"}]}