{"status": "ok", "totalResults": 2, "articles": [{"source": {"id": null, "name": "Hindustan Times"}, "author": "Neha Yadav", "title": "What is sleep paralysis? 6 tips to avoid it - Hindustan Times", "description": "What is sleep paralysis? 6 tips to avoid it", "url": "https://www.hindustantimes.com/web-stories/lifestyle/what-is-sleep-paralysis-6-tips-to-avoid-it-101722841996447.html", "urlToImage": null, "publishedAt": "2024-08-05T12:30:19Z", "content": "By Neha YadavPublished Aug 05, 2024\r\nHindustan TimesLifestylePhoto Credits: Pexels"}, {"source": {"id": null, "name": "The Indian Express"}, "author": "Lifestyle Desk", "title": "True or false: Women see more colours than men - The Indian Express", "description": "Women See More Colours? Science Explains!  Explore the fascinating link between X chromosomes, cone cells, hormones, and brain structure that potentially gives women an edge in color perception compared to men.", "url": "https://indianexpress.com/article/lifestyle/life-style/true-or-false-women-see-more-colours-than-men-9354304/", "urlToImage": "https://images.indianexpress.com/2024/05/vision-1.jpg", "publishedAt": "2024-08-05T09:00:17Z", "content": "Neuroscientist and content creator Emily McDonald in her latest reel, says, Fun fact of the day is that women can often see more colours than men and this is because the genes that are responsible fo\u2026 [+3522 chars]"}]}